authlib-stubs/METADATA.toml
authlib-stubs/__init__.pyi
authlib-stubs/consts.pyi
authlib-stubs/deprecate.pyi
authlib-stubs/py.typed
authlib-stubs/common/__init__.pyi
authlib-stubs/common/encoding.pyi
authlib-stubs/common/errors.pyi
authlib-stubs/common/security.pyi
authlib-stubs/common/urls.pyi
authlib-stubs/integrations/__init__.pyi
authlib-stubs/integrations/base_client/__init__.pyi
authlib-stubs/integrations/base_client/async_app.pyi
authlib-stubs/integrations/base_client/async_openid.pyi
authlib-stubs/integrations/base_client/errors.pyi
authlib-stubs/integrations/base_client/framework_integration.pyi
authlib-stubs/integrations/base_client/registry.pyi
authlib-stubs/integrations/base_client/sync_app.pyi
authlib-stubs/integrations/base_client/sync_openid.pyi
authlib-stubs/integrations/django_client/__init__.pyi
authlib-stubs/integrations/django_client/apps.pyi
authlib-stubs/integrations/django_client/integration.pyi
authlib-stubs/integrations/django_oauth1/__init__.pyi
authlib-stubs/integrations/django_oauth1/authorization_server.pyi
authlib-stubs/integrations/django_oauth1/nonce.pyi
authlib-stubs/integrations/django_oauth1/resource_protector.pyi
authlib-stubs/integrations/django_oauth2/__init__.pyi
authlib-stubs/integrations/django_oauth2/authorization_server.pyi
authlib-stubs/integrations/django_oauth2/endpoints.pyi
authlib-stubs/integrations/django_oauth2/requests.pyi
authlib-stubs/integrations/django_oauth2/resource_protector.pyi
authlib-stubs/integrations/django_oauth2/signals.pyi
authlib-stubs/integrations/flask_client/__init__.pyi
authlib-stubs/integrations/flask_client/apps.pyi
authlib-stubs/integrations/flask_client/integration.pyi
authlib-stubs/integrations/flask_oauth1/__init__.pyi
authlib-stubs/integrations/flask_oauth1/authorization_server.pyi
authlib-stubs/integrations/flask_oauth1/cache.pyi
authlib-stubs/integrations/flask_oauth1/resource_protector.pyi
authlib-stubs/integrations/flask_oauth2/__init__.pyi
types_authlib-1.6.6.20260130.dist-info/licenses/LICENSE
types_authlib-1.6.6.20260130.dist-info/METADATA
types_authlib-1.6.6.20260130.dist-info/WHEEL
types_authlib-1.6.6.20260130.dist-info/top_level.txt
types_authlib-1.6.6.20260130.dist-info/RECORD
